tgmix/__init__.py
tgmix/config.json
tgmix/consts.py
tgmix/main.py
tgmix/media_processor.py
tgmix/message_processor.py
tgmix/stats_processor.py
tgmix/utils.py
tgmix-0.9.1.dist-info/licenses/LICENSE
tgmix-0.9.1.dist-info/METADATA
tgmix-0.9.1.dist-info/WHEEL
tgmix-0.9.1.dist-info/entry_points.txt
tgmix-0.9.1.dist-info/top_level.txt
tgmix-0.9.1.dist-info/RECORD
