Metadata-Version: 2.4
Name: tgmix
Version: 0.9.1
Summary: A tool to process Telegram chat exports into an AI-friendly format, inspired by Repomix.
Author: damnkrat
License:                     GNU GENERAL PUBLIC LICENSE
Project-URL: Source, https://github.com/damnkrat/tgmix
Project-URL: Bug Tracker, https://github.com/damnkrat/tgmix/issues
Keywords: telegram,chat,export,llm,ai,dataset,nlp,chatgpt,gemini,grok,claude,llama
Classifier: Development Status :: 4 - Beta
Classifier: Programming Language :: Python :: 3
Classifier: Programming Language :: Python :: 3.10
Classifier: License :: OSI Approved :: GNU General Public License v3 (GPLv3)
Classifier: Operating System :: OS Independent
Classifier: Topic :: Text Processing
Classifier: Topic :: Utilities
Classifier: Intended Audience :: Developers
Classifier: Intended Audience :: Science/Research
Requires-Python: >=3.10
License-File: LICENSE
Requires-Dist: phonenumbers>=9.0.14
Requires-Dist: rs-bpe>=0.1.0
Requires-Dist: tqdm>=4.67.1
Requires-Dist: ujson>=5.11.0
Requires-Dist: MarkMyMedia>=1.1.0
Requires-Dist: python-toon>=0.1.3
Dynamic: license-file
